{
  "slug": "inflict-wounds",
  "name": "Inflict Wounds",
  "casting_config": {
    "time_value": 1,
    "time_unit": "Action",
    "components": {
      "consumed": false,
      "material": false,
      "somatic": true,
      "verbal": true
    },
    "is_concentration": false,
    "is_ritual": false
  },
  "compilation_state": {
    "status": "Valid"
  },
  "damage_instances": [
    {
      "effect_type": "Damage",
      "damage_type": "necrotic",
      "dice_count": 3,
      "dice_value": 10,
      "timing": "Instant"
    }
  ],
  "description": "Make a melee spell attack against a creature you can reach. On a hit, the target takes 3d10 necrotic damage.\n\n**At Higher Levels.** When you cast this spell using a spell slot of 2nd level or higher, the damage increases by 1d10 for each slot level above 1st.",
  "duration_config": {
    "type": "Instantaneous"
  },
  "level": 1,
  "mechanics_config": {
    "action_type": "Melee Spell Attack"
  },
  "range_config": {
    "type": "Touch"
  },
  "scaling_config": {
    "dice_count": 1,
    "dice_value": 10,
    "method": "Per Slot Level",
    "scales": true,
    "type": "Dice"
  },
  "school": "necromancy"
}