{
  "kind": "collectionType",
  "collectionName": "items",
  "info": {
    "singularName": "item",
    "pluralName": "items",
    "displayName": "Item",
    "description": "Unified item model (Equipment, Magic Items, Loot, Tools)"
  },
  "options": {
    "draftAndPublish": false
  },
  "pluginOptions": {
    "i18n": {
      "localized": true
    }
  },
  "attributes": {
    "name": {
      "type": "string",
      "required": true,
      "pluginOptions": {
        "i18n": {
          "localized": true
        }
      }
    },
    "slug": {
      "type": "uid",
      "targetField": "name",
      "required": true
    },
    "description": {
      "type": "richtext",
      "pluginOptions": {
        "i18n": {
          "localized": true
        }
      }
    },
    "lore": {
      "type": "richtext",
      "pluginOptions": {
        "i18n": {
          "localized": true
        }
      }
    },
    "type": {
      "type": "enumeration",
      "enum": ["weapon", "armor", "consumable", "tool", "loot", "spell_scroll", "feature", "container", "wondrous_item", "ring", "rod", "staff", "wand", "potion"],
      "required": true,
      "default": "loot"
    },
    "rarity": {
      "type": "enumeration",
      "enum": ["common", "uncommon", "rare", "very_rare", "legendary", "artifact"],
      "default": "common"
    },
    "value": {
      "type": "integer",
      "default": 0
    },
    "weight": {
      "type": "float",
      "default": 0
    },
    "size": {
      "type": "enumeration",
      "enum": ["Fine", "Diminutive", "Tiny", "Small", "Medium", "Large", "Huge", "Gargantuan", "Colossal"],
      "default": "Medium"
    },
    "equipment_data": {
      "type": "component",
      "repeatable": false,
      "component": "game.equipment-data"
    },
    "spell_data": {
      "type": "component",
      "repeatable": false,
      "component": "game.spell-data"
    },
    "custom_data": {
      "type": "json"
    },
    "embedding": {
      "type": "json",
      "private": true
    },
    "compilation_state": {
      "type": "component",
      "repeatable": false,
      "component": "game.compilation-state"
    },
    "tags": {
      "type": "relation",
      "relation": "manyToMany",
      "target": "api::tag.tag",
      "inversedBy": "items"
    },
    "pixel_generator": {
      "type": "customField",
      "customField": "plugin::map-explorer.pixel-generator"
    }
  }
}
